
{
"exchange_name": "papertrader", "product_id": "TCS-FUT","name": "TCS", "current_market_rate": 3526.790000,
"cur_candle_time": 1760604600, "cur_candle_vol": 0.000000, "num_candles": 5090,
"num_buy_req": 18, "num_buy_req_reject": 4,
"num_sell_req": 8, "num_sell_req_reject": 0,
"num_buy_order": 14, "num_buy_order_success": 14, "num_buy_order_failed": 0,
"num_sell_order": 8, "num_sell_order_success": 8, "num_sell_order_failed": 0,
"num_take_profit_hit": 0, "num_stop_loss_hit": 0,
"num_success_trade": 3, "num_failed_trade": 5,
"cur_buy_and_hold_profit": 0.000000,
"trading_paused_buy": 0, "trading_paused_sell": 0,
"fund":
{
"initial_value":1000000.000000,"current_value":861168.620000,"current_hold_value":0.000000, "total_traded_value":512287.680000, "fee_accrued": 0.000000,
"current_realized_profit":-495.980000,"current_unrealized_profit":0.000000, "total_profit":0.000000,
"current_avg_buy_price":3518.011440,"latest_buy_price":3521.800000,
"fund_liquidity_percent":0, "max_per_buy_fund_value":25000
},
"asset":{
"initial_size":0.000000, "current_size":39.000000, "hold_size": 0.000000, "current_hold_size":0.000000,
"max_per_trade_size":50.000000, "min_per_trade_size":1.000000, "latest_traded_size":7.000000, "total_traded_size":145.000000
},
"order_book":
{"position_all": 14, "open": 6, "close_pending": 0, "closed": 8}
}